{
  "key": "plastic_surgery",
  "display_name": "Plastic Surgery",
  "version": "1.0",
  "sections": [
    {
      "id": "chief_complaint",
      "title": "Chief Complaint",
      "required": true,
      "visual_trigger_keywords": [],
      "description": "Primary presenting complaint in the patient's own words"
    },
    {
      "id": "hpi",
      "title": "History of Present Illness",
      "required": true,
      "visual_trigger_keywords": [],
      "description": "Onset, duration, character, radiation, associated symptoms, timing, exacerbating/relieving factors, severity"
    },
    {
      "id": "wound_assessment",
      "title": "Wound Assessment",
      "required": true,
      "visual_trigger_keywords": [
        "wound", "incision", "flap", "graft", "donor site",
        "wound edges", "approximation", "granulation", "epithelialization",
        "dimensions", "measuring", "depth", "drainage", "exudate",
        "erythema", "induration", "perfusion", "capillary refill",
        "undermining", "tunneling", "eschar", "slough", "necrosis",
        "maceration", "dehiscence", "serous", "serosanguineous", "purulent",
        "looking at", "right here", "this area"
      ],
      "description": "Anatomical location; dimensions as length × width × depth in cm; wound-bed tissue types and proportions (granulation, slough, eschar, necrosis); exudate amount and character (serous/serosanguineous/purulent, colour, odour); wound edges (approximated, undermining, tunnelling); periwound skin; flap/graft viability (colour match, capillary refill, perfusion); signs of infection — described only as stated"
    },
    {
      "id": "imaging_review",
      "title": "Imaging Review",
      "required": true,
      "visual_trigger_keywords": [
        "X-ray", "MRI", "CT", "imaging", "looking at", "pulling up"
      ],
      "description": "Description of imaging findings as literally observed on screen — modality, laterality, findings described only"
    },
    {
      "id": "assessment",
      "title": "Assessment",
      "required": true,
      "visual_trigger_keywords": [],
      "description": "Working diagnosis as explicitly stated by the physician, verbatim. Do not add differentials the physician did not voice"
    },
    {
      "id": "plan",
      "title": "Plan",
      "required": true,
      "visual_trigger_keywords": [],
      "description": "Treatment plan, investigations ordered, referrals, follow-up timeline as stated by the physician"
    }
  ]
}
